moleculeresolver/SqliteMoleculeCache.py
moleculeresolver/__init__.py
moleculeresolver/molecule.py
moleculeresolver/moleculeresolver.py
moleculeresolver/opsin-cli-2.8.0-jar-with-dependencies.jar
moleculeresolver/rdkitmods.py
molecule_resolver-0.4.1.dist-info/METADATA
molecule_resolver-0.4.1.dist-info/WHEEL
molecule_resolver-0.4.1.dist-info/licenses/LICENSE.txt
molecule_resolver-0.4.1.dist-info/RECORD
