Metadata-Version: 2.4
Name: molecule-resolver
Version: 0.4.1
Summary: A package to use several web services to find molecule structures, synonyms and CAS.
License: MIT
License-File: LICENSE.txt
Author: Simon Muller
Author-email: simon.mueller@tuhh.de
Requires-Python: >=3.10,<3.14
Classifier: License :: OSI Approved :: MIT License
Classifier: Programming Language :: Python :: 3
Classifier: Programming Language :: Python :: 3.10
Classifier: Programming Language :: Python :: 3.11
Classifier: Programming Language :: Python :: 3.12
Classifier: Programming Language :: Python :: 3.13
Requires-Dist: openpyxl (>=3.1.2,<4.0.0)
Requires-Dist: prompt-toolkit (>=3.0.39,<4.0.0)
Requires-Dist: rdkit (>=2023.3.3)
Requires-Dist: regex (>=2023.10.3,<2024.0.0)
Requires-Dist: requests (>=2.31.0,<3.0.0)
Requires-Dist: tqdm (>=4.66.3,<5.0.0)
Requires-Dist: urllib3 (>=2.0.6,<3.0.0)
Requires-Dist: xmltodict (>=0.13.0,<0.14.0)
